rach_pack/__init__.py
rach_pack/main.py
rach_pack-0.4.0.dist-info/METADATA
rach_pack-0.4.0.dist-info/WHEEL
rach_pack-0.4.0.dist-info/top_level.txt
rach_pack-0.4.0.dist-info/RECORD
