Metadata-Version: 2.1
Name: rach-pack
Version: 0.4.0
Summary: A sample Python project for rach pack
Home-page: https://github.com/r-mhjn/QuizCreator
Author: Rac
Author-email: rachitmahajan6399@gmail.com
License: UNKNOWN
Platform: UNKNOWN
Classifier: Development Status :: 3 - Alpha
Classifier: Intended Audience :: Developers
Classifier: License :: OSI Approved :: MIT License
Classifier: Programming Language :: Python :: 3
Classifier: Programming Language :: Python :: 3.7
Classifier: Programming Language :: Python :: 3.8
Classifier: Programming Language :: Python :: 3.9
